MANIFEST.in
setup.py
metapipe/__init__.py
metapipe/__main__.py
metapipe/app.py
metapipe/parser.py
metapipe/runtime.py
metapipe.egg-info/PKG-INFO
metapipe.egg-info/SOURCES.txt
metapipe.egg-info/dependency_links.txt
metapipe.egg-info/entry_points.txt
metapipe.egg-info/requires.txt
metapipe.egg-info/top_level.txt
metapipe/models/__init__.py
metapipe/models/command.py
metapipe/models/command_template.py
metapipe/models/command_template_factory.py
metapipe/models/grammar.py
metapipe/models/job.py
metapipe/models/job_template.py
metapipe/models/local_job.py
metapipe/models/pbs_job.py
metapipe/models/queue.py
metapipe/models/reporting.py
metapipe/models/sge_job.py
metapipe/models/tokens.py
metapipe/templates/__init__.py
metapipe/templates/__init__.pyc
metapipe/templates/output_script.tmpl.sh
metapipe/templates/progress-report.tmpl.html
test/__init__.py
test/fixtures.py
test/mocks.py
test/test_app.py
test/test_command.py
test/test_command_template.py
test/test_command_template_factory.py
test/test_grammar.py
test/test_job.py
test/test_local_job.py
test/test_parser.py
test/test_pbs_job.py
test/test_queue.py
test/test_runtime.py
test/test_sge_job.py
test/test_template.py
test/test_tokens.py