Metadata-Version: 1.0
Name: metapipe
Version: 1.3.post1
Summary: A pipeline for building analysis pipelines.
Home-page: https://github.com/TorkamaniLab/metapipe
Author: Brian Schrader
Author-email: brian@brianschrader.com
License: UNKNOWN
Platform: UNKNOWN
